{"frames": [

{
	"filename": "h_5.png",
	"frame": {"x":0,"y":0,"w":646,"h":830},
	"rotated": false,
	"trimmed": false,
	"spriteSourceSize": {"x":0,"y":0,"w":646,"h":830},
	"sourceSize": {"w":646,"h":830}
},
{
	"filename": "h_6.png",
	"frame": {"x":646,"y":0,"w":646,"h":830},
	"rotated": false,
	"trimmed": false,
	"spriteSourceSize": {"x":0,"y":0,"w":646,"h":830},
	"sourceSize": {"w":646,"h":830}
},
{
	"filename": "h_7.png",
	"frame": {"x":1292,"y":0,"w":646,"h":830},
	"rotated": false,
	"trimmed": false,
	"spriteSourceSize": {"x":0,"y":0,"w":646,"h":830},
	"sourceSize": {"w":646,"h":830}
},
{
	"filename": "h_b_1.png",
	"frame": {"x":0,"y":830,"w":646,"h":830},
	"rotated": false,
	"trimmed": false,
	"spriteSourceSize": {"x":0,"y":0,"w":646,"h":830},
	"sourceSize": {"w":646,"h":830}
},
{
	"filename": "h_b_3.png",
	"frame": {"x":646,"y":830,"w":646,"h":830},
	"rotated": false,
	"trimmed": false,
	"spriteSourceSize": {"x":0,"y":0,"w":646,"h":830},
	"sourceSize": {"w":646,"h":830}
},
{
	"filename": "h_b_6.png",
	"frame": {"x":1292,"y":830,"w":646,"h":830},
	"rotated": false,
	"trimmed": false,
	"spriteSourceSize": {"x":0,"y":0,"w":646,"h":830},
	"sourceSize": {"w":646,"h":830}
}],
"meta": {
	"app": "http://www.codeandweb.com/texturepacker",
	"version": "1.0",
	"image": "doll_cindy_9.png",
	"format": "RGBA8888",
	"size": {"w":1938,"h":1660},
	"scale": "1",
	"smartupdate": "$TexturePacker:SmartUpdate:fc387c2bf78008eb0eb62e1131f23736:e07ddf394a5dd7f05246f2df1372d115:c518f40f95ad9be3eb2e4155ed702da9$"
}
}
