{"frames": [

{
	"filename": "ac_1.png",
	"frame": {"x":0,"y":0,"w":275,"h":670},
	"rotated": false,
	"trimmed": false,
	"spriteSourceSize": {"x":0,"y":0,"w":275,"h":670},
	"sourceSize": {"w":275,"h":670},
	"pivot": {"x":0.5,"y":0.5}
},
{
	"filename": "bb_1.png",
	"frame": {"x":275,"y":0,"w":275,"h":670},
	"rotated": false,
	"trimmed": false,
	"spriteSourceSize": {"x":0,"y":0,"w":275,"h":670},
	"sourceSize": {"w":275,"h":670},
	"pivot": {"x":0.5,"y":0.5}
},
{
	"filename": "bb_2.png",
	"frame": {"x":550,"y":0,"w":275,"h":670},
	"rotated": false,
	"trimmed": false,
	"spriteSourceSize": {"x":0,"y":0,"w":275,"h":670},
	"sourceSize": {"w":275,"h":670},
	"pivot": {"x":0.5,"y":0.5}
},
{
	"filename": "body.png",
	"frame": {"x":825,"y":0,"w":275,"h":670},
	"rotated": false,
	"trimmed": false,
	"spriteSourceSize": {"x":0,"y":0,"w":275,"h":670},
	"sourceSize": {"w":275,"h":670},
	"pivot": {"x":0.5,"y":0.5}
},
{
	"filename": "d_0.png",
	"frame": {"x":1100,"y":0,"w":275,"h":670},
	"rotated": false,
	"trimmed": false,
	"spriteSourceSize": {"x":0,"y":0,"w":275,"h":670},
	"sourceSize": {"w":275,"h":670},
	"pivot": {"x":0.5,"y":0.5}
},
{
	"filename": "d_1.png",
	"frame": {"x":1375,"y":0,"w":275,"h":670},
	"rotated": false,
	"trimmed": false,
	"spriteSourceSize": {"x":0,"y":0,"w":275,"h":670},
	"sourceSize": {"w":275,"h":670},
	"pivot": {"x":0.5,"y":0.5}
},
{
	"filename": "d_2.png",
	"frame": {"x":1650,"y":0,"w":275,"h":670},
	"rotated": false,
	"trimmed": false,
	"spriteSourceSize": {"x":0,"y":0,"w":275,"h":670},
	"sourceSize": {"w":275,"h":670},
	"pivot": {"x":0.5,"y":0.5}
},
{
	"filename": "d_3.png",
	"frame": {"x":0,"y":670,"w":275,"h":670},
	"rotated": false,
	"trimmed": false,
	"spriteSourceSize": {"x":0,"y":0,"w":275,"h":670},
	"sourceSize": {"w":275,"h":670},
	"pivot": {"x":0.5,"y":0.5}
},
{
	"filename": "d_4.png",
	"frame": {"x":275,"y":670,"w":275,"h":670},
	"rotated": false,
	"trimmed": false,
	"spriteSourceSize": {"x":0,"y":0,"w":275,"h":670},
	"sourceSize": {"w":275,"h":670},
	"pivot": {"x":0.5,"y":0.5}
},
{
	"filename": "d_5.png",
	"frame": {"x":550,"y":670,"w":275,"h":670},
	"rotated": false,
	"trimmed": false,
	"spriteSourceSize": {"x":0,"y":0,"w":275,"h":670},
	"sourceSize": {"w":275,"h":670},
	"pivot": {"x":0.5,"y":0.5}
},
{
	"filename": "d_6.png",
	"frame": {"x":825,"y":670,"w":275,"h":670},
	"rotated": false,
	"trimmed": false,
	"spriteSourceSize": {"x":0,"y":0,"w":275,"h":670},
	"sourceSize": {"w":275,"h":670},
	"pivot": {"x":0.5,"y":0.5}
},
{
	"filename": "d_7.png",
	"frame": {"x":1100,"y":670,"w":275,"h":670},
	"rotated": false,
	"trimmed": false,
	"spriteSourceSize": {"x":0,"y":0,"w":275,"h":670},
	"sourceSize": {"w":275,"h":670},
	"pivot": {"x":0.5,"y":0.5}
},
{
	"filename": "d_8.png",
	"frame": {"x":1375,"y":670,"w":275,"h":670},
	"rotated": false,
	"trimmed": false,
	"spriteSourceSize": {"x":0,"y":0,"w":275,"h":670},
	"sourceSize": {"w":275,"h":670},
	"pivot": {"x":0.5,"y":0.5}
},
{
	"filename": "gs_1.png",
	"frame": {"x":1650,"y":670,"w":275,"h":670},
	"rotated": false,
	"trimmed": false,
	"spriteSourceSize": {"x":0,"y":0,"w":275,"h":670},
	"sourceSize": {"w":275,"h":670},
	"pivot": {"x":0.5,"y":0.5}
},
{
	"filename": "h_0.png",
	"frame": {"x":0,"y":1340,"w":275,"h":670},
	"rotated": false,
	"trimmed": false,
	"spriteSourceSize": {"x":0,"y":0,"w":275,"h":670},
	"sourceSize": {"w":275,"h":670},
	"pivot": {"x":0.5,"y":0.5}
},
{
	"filename": "h_1.png",
	"frame": {"x":275,"y":1340,"w":275,"h":670},
	"rotated": false,
	"trimmed": false,
	"spriteSourceSize": {"x":0,"y":0,"w":275,"h":670},
	"sourceSize": {"w":275,"h":670},
	"pivot": {"x":0.5,"y":0.5}
},
{
	"filename": "h_2.png",
	"frame": {"x":550,"y":1340,"w":275,"h":670},
	"rotated": false,
	"trimmed": false,
	"spriteSourceSize": {"x":0,"y":0,"w":275,"h":670},
	"sourceSize": {"w":275,"h":670},
	"pivot": {"x":0.5,"y":0.5}
},
{
	"filename": "h_3.png",
	"frame": {"x":825,"y":1340,"w":275,"h":670},
	"rotated": false,
	"trimmed": false,
	"spriteSourceSize": {"x":0,"y":0,"w":275,"h":670},
	"sourceSize": {"w":275,"h":670},
	"pivot": {"x":0.5,"y":0.5}
},
{
	"filename": "h_4.png",
	"frame": {"x":1100,"y":1340,"w":275,"h":670},
	"rotated": false,
	"trimmed": false,
	"spriteSourceSize": {"x":0,"y":0,"w":275,"h":670},
	"sourceSize": {"w":275,"h":670},
	"pivot": {"x":0.5,"y":0.5}
},
{
	"filename": "h_5.png",
	"frame": {"x":1375,"y":1340,"w":275,"h":670},
	"rotated": false,
	"trimmed": false,
	"spriteSourceSize": {"x":0,"y":0,"w":275,"h":670},
	"sourceSize": {"w":275,"h":670},
	"pivot": {"x":0.5,"y":0.5}
},
{
	"filename": "h_6.png",
	"frame": {"x":1650,"y":1340,"w":275,"h":670},
	"rotated": false,
	"trimmed": false,
	"spriteSourceSize": {"x":0,"y":0,"w":275,"h":670},
	"sourceSize": {"w":275,"h":670},
	"pivot": {"x":0.5,"y":0.5}
}],
"meta": {
	"app": "http://www.codeandweb.com/texturepacker",
	"version": "1.0",
	"image": "doll_ariel.png",
	"format": "RGBA8888",
	"size": {"w":1925,"h":2010},
	"scale": "1",
	"smartupdate": "$TexturePacker:SmartUpdate:59ec7eef97eab9594120209cc91b8b8f:621569c99a707f73ce70a971b0af27aa:8f59871ed412c3c1fe23947fe0cc8699$"
}
}
