{
"frames": [
	{
		"filename": "an_bag_1.png",
		"frame": {"x":128, "y":1722, "w":121, "h":113},
		"spriteSourceSize": {"x":0,"y":0,"w":121,"h":113},
		"sourceSize": {"w":121,"h":113}
	},
	{
		"filename": "an_bag_2.png",
		"frame": {"x":254, "y":1537, "w":114, "h":113},
		"spriteSourceSize": {"x":0,"y":0,"w":114,"h":113},
		"sourceSize": {"w":114,"h":113}
	},
	{
		"filename": "an_bag_3.png",
		"frame": {"x":130, "y":1294, "w":120, "h":121},
		"spriteSourceSize": {"x":0,"y":0,"w":120,"h":121},
		"sourceSize": {"w":120,"h":121}
	},
	{
		"filename": "an_bag_4.png",
		"frame": {"x":0, "y":1040, "w":138, "h":127},
		"spriteSourceSize": {"x":0,"y":0,"w":138,"h":127},
		"sourceSize": {"w":138,"h":127}
	},
	{
		"filename": "an_bag_5.png",
		"frame": {"x":0, "y":1172, "w":128, "h":117},
		"spriteSourceSize": {"x":0,"y":0,"w":128,"h":117},
		"sourceSize": {"w":128,"h":117}
	},
	{
		"filename": "an_bag_6.png",
		"frame": {"x":0, "y":1294, "w":125, "h":121},
		"spriteSourceSize": {"x":0,"y":0,"w":125,"h":121},
		"sourceSize": {"w":125,"h":121}
	},
	{
		"filename": "an_bag_7.png",
		"frame": {"x":254, "y":1655, "w":110, "h":121},
		"spriteSourceSize": {"x":0,"y":0,"w":110,"h":121},
		"sourceSize": {"w":110,"h":121}
	},
	{
		"filename": "an_bag_8.png",
		"frame": {"x":368, "y":1904, "w":99, "h":116},
		"spriteSourceSize": {"x":0,"y":0,"w":99,"h":116},
		"sourceSize": {"w":99,"h":116}
	},
	{
		"filename": "an_shoe_1.png",
		"frame": {"x":365, "y":1301, "w":98, "h":110},
		"spriteSourceSize": {"x":0,"y":0,"w":98,"h":110},
		"sourceSize": {"w":98,"h":110}
	},
	{
		"filename": "an_shoe_2.png",
		"frame": {"x":469, "y":690, "w":95, "h":135},
		"spriteSourceSize": {"x":0,"y":0,"w":95,"h":135},
		"sourceSize": {"w":95,"h":135}
	},
	{
		"filename": "an_shoe_3.png",
		"frame": {"x":369, "y":1655, "w":97, "h":124},
		"spriteSourceSize": {"x":0,"y":0,"w":97,"h":124},
		"sourceSize": {"w":97,"h":124}
	},
	{
		"filename": "an_shoe_4.png",
		"frame": {"x":375, "y":1040, "w":95, "h":118},
		"spriteSourceSize": {"x":0,"y":0,"w":95,"h":118},
		"sourceSize": {"w":95,"h":118}
	},
	{
		"filename": "an_shoe_5.png",
		"frame": {"x":365, "y":1175, "w":102, "h":121},
		"spriteSourceSize": {"x":0,"y":0,"w":102,"h":121},
		"sourceSize": {"w":102,"h":121}
	},
	{
		"filename": "an_shoe_6.png",
		"frame": {"x":373, "y":1416, "w":97, "h":117},
		"spriteSourceSize": {"x":0,"y":0,"w":97,"h":117},
		"sourceSize": {"w":97,"h":117}
	},
	{
		"filename": "an_shoe_7.png",
		"frame": {"x":469, "y":830, "w":93, "h":127},
		"spriteSourceSize": {"x":0,"y":0,"w":93,"h":127},
		"sourceSize": {"w":93,"h":127}
	},
	{
		"filename": "an_shoe_8.png",
		"frame": {"x":471, "y":1689, "w":91, "h":131},
		"spriteSourceSize": {"x":0,"y":0,"w":91,"h":131},
		"sourceSize": {"w":91,"h":131}
	},
	{
		"filename": "chest_2.png",
		"frame": {"x":0, "y":0, "w":484, "h":685},
		"spriteSourceSize": {"x":0,"y":0,"w":484,"h":685},
		"sourceSize": {"w":484,"h":685}
	},
	{
		"filename": "cl_4.png",
		"frame": {"x":0, "y":690, "w":464, "h":345},
		"spriteSourceSize": {"x":0,"y":0,"w":464,"h":345},
		"sourceSize": {"w":464,"h":345}
	},
	{
		"filename": "el_bag_1.png",
		"frame": {"x":0, "y":1420, "w":125, "h":179},
		"spriteSourceSize": {"x":0,"y":0,"w":125,"h":179},
		"sourceSize": {"w":125,"h":179}
	},
	{
		"filename": "el_bag_2.png",
		"frame": {"x":252, "y":1420, "w":115, "h":112},
		"spriteSourceSize": {"x":0,"y":0,"w":115,"h":112},
		"sourceSize": {"w":115,"h":112}
	},
	{
		"filename": "el_bag_3.png",
		"frame": {"x":0, "y":1604, "w":124, "h":113},
		"spriteSourceSize": {"x":0,"y":0,"w":124,"h":113},
		"sourceSize": {"w":124,"h":113}
	},
	{
		"filename": "el_bag_4.png",
		"frame": {"x":471, "y":1538, "w":92, "h":146},
		"spriteSourceSize": {"x":0,"y":0,"w":92,"h":146},
		"sourceSize": {"w":92,"h":146}
	},
	{
		"filename": "el_bag_5.png",
		"frame": {"x":255, "y":1292, "w":105, "h":122},
		"spriteSourceSize": {"x":0,"y":0,"w":105,"h":122},
		"sourceSize": {"w":105,"h":122}
	},
	{
		"filename": "el_bag_6.png",
		"frame": {"x":143, "y":1040, "w":115, "h":121},
		"spriteSourceSize": {"x":0,"y":0,"w":115,"h":121},
		"sourceSize": {"w":115,"h":121}
	},
	{
		"filename": "el_bag_7.png",
		"frame": {"x":143, "y":1166, "w":115, "h":121},
		"spriteSourceSize": {"x":0,"y":0,"w":115,"h":121},
		"sourceSize": {"w":115,"h":121}
	},
	{
		"filename": "el_bag_8.png",
		"frame": {"x":472, "y":1825, "w":67, "h":159},
		"spriteSourceSize": {"x":0,"y":0,"w":67,"h":159},
		"sourceSize": {"w":67,"h":159}
	},
	{
		"filename": "el_shoe_1.png",
		"frame": {"x":254, "y":1904, "w":109, "h":116},
		"spriteSourceSize": {"x":0,"y":0,"w":109,"h":116},
		"sourceSize": {"w":109,"h":116}
	},
	{
		"filename": "el_shoe_2.png",
		"frame": {"x":128, "y":1954, "w":117, "h":74},
		"spriteSourceSize": {"x":0,"y":0,"w":117,"h":74},
		"sourceSize": {"w":117,"h":74}
	},
	{
		"filename": "el_shoe_3.png",
		"frame": {"x":254, "y":1781, "w":110, "h":118},
		"spriteSourceSize": {"x":0,"y":0,"w":110,"h":118},
		"sourceSize": {"w":110,"h":118}
	},
	{
		"filename": "el_shoe_4.png",
		"frame": {"x":263, "y":1040, "w":107, "h":130},
		"spriteSourceSize": {"x":0,"y":0,"w":107,"h":130},
		"sourceSize": {"w":107,"h":130}
	},
	{
		"filename": "el_shoe_5.png",
		"frame": {"x":128, "y":1840, "w":121, "h":109},
		"spriteSourceSize": {"x":0,"y":0,"w":121,"h":109},
		"sourceSize": {"w":121,"h":109}
	},
	{
		"filename": "el_shoe_6.png",
		"frame": {"x":130, "y":1420, "w":117, "h":124},
		"spriteSourceSize": {"x":0,"y":0,"w":117,"h":124},
		"sourceSize": {"w":117,"h":124}
	},
	{
		"filename": "el_shoe_7.png",
		"frame": {"x":129, "y":1604, "w":120, "h":90},
		"spriteSourceSize": {"x":0,"y":0,"w":120,"h":90},
		"sourceSize": {"w":120,"h":90}
	},
	{
		"filename": "el_shoe_8.png",
		"frame": {"x":0, "y":1903, "w":123, "h":89},
		"spriteSourceSize": {"x":0,"y":0,"w":123,"h":89},
		"sourceSize": {"w":123,"h":89}
	},
	{
		"filename": "mmmm.png",
		"frame": {"x":0, "y":1722, "w":123, "h":176},
		"spriteSourceSize": {"x":0,"y":0,"w":123,"h":176},
		"sourceSize": {"w":123,"h":176}
	}

],
"meta": {
	"image": "dress_2_state.png",
	"size": {"w": 2048, "h": 2048},
	"scale": "1"
}
}