{"frames": [

{
	"filename": "chest.png",
	"frame": {"x":0,"y":0,"w":516,"h":781},
	"rotated": false,
	"trimmed": false,
	"spriteSourceSize": {"x":0,"y":0,"w":516,"h":781},
	"sourceSize": {"w":516,"h":781},
	"pivot": {"x":0.5,"y":0.5}
},
{
	"filename": "cross.png",
	"frame": {"x":516,"y":0,"w":341,"h":421},
	"rotated": false,
	"trimmed": false,
	"spriteSourceSize": {"x":0,"y":0,"w":341,"h":421},
	"sourceSize": {"w":341,"h":421},
	"pivot": {"x":0.5,"y":0.5}
},
{
	"filename": "dress_1.png",
	"frame": {"x":857,"y":0,"w":247,"h":382},
	"rotated": false,
	"trimmed": false,
	"spriteSourceSize": {"x":0,"y":0,"w":247,"h":382},
	"sourceSize": {"w":247,"h":382},
	"pivot": {"x":0.5,"y":0.5}
},
{
	"filename": "dress_2.png",
	"frame": {"x":1104,"y":0,"w":219,"h":410},
	"rotated": false,
	"trimmed": false,
	"spriteSourceSize": {"x":0,"y":0,"w":219,"h":410},
	"sourceSize": {"w":219,"h":410},
	"pivot": {"x":0.5,"y":0.5}
},
{
	"filename": "dress_3.png",
	"frame": {"x":1323,"y":0,"w":249,"h":390},
	"rotated": false,
	"trimmed": false,
	"spriteSourceSize": {"x":0,"y":0,"w":249,"h":390},
	"sourceSize": {"w":249,"h":390},
	"pivot": {"x":0.5,"y":0.5}
},
{
	"filename": "dress_4.png",
	"frame": {"x":1572,"y":0,"w":196,"h":384},
	"rotated": false,
	"trimmed": false,
	"spriteSourceSize": {"x":0,"y":0,"w":196,"h":384},
	"sourceSize": {"w":196,"h":384},
	"pivot": {"x":0.5,"y":0.5}
},
{
	"filename": "dress_5.png",
	"frame": {"x":1768,"y":0,"w":161,"h":255},
	"rotated": false,
	"trimmed": false,
	"spriteSourceSize": {"x":0,"y":0,"w":161,"h":255},
	"sourceSize": {"w":161,"h":255},
	"pivot": {"x":0.5,"y":0.5}
},
{
	"filename": "dress_6.png",
	"frame": {"x":0,"y":781,"w":244,"h":357},
	"rotated": false,
	"trimmed": false,
	"spriteSourceSize": {"x":0,"y":0,"w":244,"h":357},
	"sourceSize": {"w":244,"h":357},
	"pivot": {"x":0.5,"y":0.5}
},
{
	"filename": "glove_1.png",
	"frame": {"x":244,"y":781,"w":113,"h":127},
	"rotated": false,
	"trimmed": false,
	"spriteSourceSize": {"x":0,"y":0,"w":113,"h":127},
	"sourceSize": {"w":113,"h":127},
	"pivot": {"x":0.5,"y":0.5}
},
{
	"filename": "hair_1.png",
	"frame": {"x":357,"y":781,"w":208,"h":305},
	"rotated": false,
	"trimmed": false,
	"spriteSourceSize": {"x":0,"y":0,"w":208,"h":305},
	"sourceSize": {"w":208,"h":305},
	"pivot": {"x":0.5,"y":0.5}
},
{
	"filename": "hair_2.png",
	"frame": {"x":565,"y":781,"w":208,"h":305},
	"rotated": false,
	"trimmed": false,
	"spriteSourceSize": {"x":0,"y":0,"w":208,"h":305},
	"sourceSize": {"w":208,"h":305},
	"pivot": {"x":0.5,"y":0.5}
},
{
	"filename": "hair_3.png",
	"frame": {"x":773,"y":781,"w":208,"h":305},
	"rotated": false,
	"trimmed": false,
	"spriteSourceSize": {"x":0,"y":0,"w":208,"h":305},
	"sourceSize": {"w":208,"h":305},
	"pivot": {"x":0.5,"y":0.5}
},
{
	"filename": "hair_4.png",
	"frame": {"x":981,"y":781,"w":208,"h":305},
	"rotated": false,
	"trimmed": false,
	"spriteSourceSize": {"x":0,"y":0,"w":208,"h":305},
	"sourceSize": {"w":208,"h":305},
	"pivot": {"x":0.5,"y":0.5}
},
{
	"filename": "hair_5.png",
	"frame": {"x":1189,"y":781,"w":208,"h":305},
	"rotated": false,
	"trimmed": false,
	"spriteSourceSize": {"x":0,"y":0,"w":208,"h":305},
	"sourceSize": {"w":208,"h":305},
	"pivot": {"x":0.5,"y":0.5}
},
{
	"filename": "hat_1.png",
	"frame": {"x":1397,"y":781,"w":134,"h":81},
	"rotated": false,
	"trimmed": false,
	"spriteSourceSize": {"x":0,"y":0,"w":134,"h":81},
	"sourceSize": {"w":134,"h":81},
	"pivot": {"x":0.5,"y":0.5}
},
{
	"filename": "jack_1.png",
	"frame": {"x":1531,"y":781,"w":208,"h":307},
	"rotated": false,
	"trimmed": false,
	"spriteSourceSize": {"x":0,"y":0,"w":208,"h":307},
	"sourceSize": {"w":208,"h":307},
	"pivot": {"x":0.5,"y":0.5}
},
{
	"filename": "jack_2.png",
	"frame": {"x":1739,"y":781,"w":188,"h":202},
	"rotated": false,
	"trimmed": false,
	"spriteSourceSize": {"x":0,"y":0,"w":188,"h":202},
	"sourceSize": {"w":188,"h":202},
	"pivot": {"x":0.5,"y":0.5}
},
{
	"filename": "jew_1.png",
	"frame": {"x":0,"y":1138,"w":90,"h":142},
	"rotated": false,
	"trimmed": false,
	"spriteSourceSize": {"x":0,"y":0,"w":90,"h":142},
	"sourceSize": {"w":90,"h":142},
	"pivot": {"x":0.5,"y":0.5}
},
{
	"filename": "jew_2.png",
	"frame": {"x":90,"y":1138,"w":90,"h":142},
	"rotated": false,
	"trimmed": false,
	"spriteSourceSize": {"x":0,"y":0,"w":90,"h":142},
	"sourceSize": {"w":90,"h":142},
	"pivot": {"x":0.5,"y":0.5}
},
{
	"filename": "jew_3.png",
	"frame": {"x":180,"y":1138,"w":90,"h":142},
	"rotated": false,
	"trimmed": false,
	"spriteSourceSize": {"x":0,"y":0,"w":90,"h":142},
	"sourceSize": {"w":90,"h":142},
	"pivot": {"x":0.5,"y":0.5}
},
{
	"filename": "neck_1.png",
	"frame": {"x":270,"y":1138,"w":131,"h":195},
	"rotated": false,
	"trimmed": false,
	"spriteSourceSize": {"x":0,"y":0,"w":131,"h":195},
	"sourceSize": {"w":131,"h":195},
	"pivot": {"x":0.5,"y":0.5}
},
{
	"filename": "neck_2.png",
	"frame": {"x":401,"y":1138,"w":154,"h":102},
	"rotated": false,
	"trimmed": false,
	"spriteSourceSize": {"x":0,"y":0,"w":154,"h":102},
	"sourceSize": {"w":154,"h":102},
	"pivot": {"x":0.5,"y":0.5}
},
{
	"filename": "neck_3.png",
	"frame": {"x":555,"y":1138,"w":122,"h":99},
	"rotated": false,
	"trimmed": false,
	"spriteSourceSize": {"x":0,"y":0,"w":122,"h":99},
	"sourceSize": {"w":122,"h":99},
	"pivot": {"x":0.5,"y":0.5}
},
{
	"filename": "shoe_1.png",
	"frame": {"x":677,"y":1138,"w":88,"h":84},
	"rotated": false,
	"trimmed": false,
	"spriteSourceSize": {"x":0,"y":0,"w":88,"h":84},
	"sourceSize": {"w":88,"h":84},
	"pivot": {"x":0.5,"y":0.5}
},
{
	"filename": "shoe_2.png",
	"frame": {"x":765,"y":1138,"w":97,"h":94},
	"rotated": false,
	"trimmed": false,
	"spriteSourceSize": {"x":0,"y":0,"w":97,"h":94},
	"sourceSize": {"w":97,"h":94},
	"pivot": {"x":0.5,"y":0.5}
},
{
	"filename": "shoe_3.png",
	"frame": {"x":862,"y":1138,"w":88,"h":96},
	"rotated": false,
	"trimmed": false,
	"spriteSourceSize": {"x":0,"y":0,"w":88,"h":96},
	"sourceSize": {"w":88,"h":96},
	"pivot": {"x":0.5,"y":0.5}
},
{
	"filename": "shoe_4.png",
	"frame": {"x":950,"y":1138,"w":99,"h":87},
	"rotated": false,
	"trimmed": false,
	"spriteSourceSize": {"x":0,"y":0,"w":99,"h":87},
	"sourceSize": {"w":99,"h":87},
	"pivot": {"x":0.5,"y":0.5}
},
{
	"filename": "shoe_5.png",
	"frame": {"x":1049,"y":1138,"w":101,"h":88},
	"rotated": false,
	"trimmed": false,
	"spriteSourceSize": {"x":0,"y":0,"w":101,"h":88},
	"sourceSize": {"w":101,"h":88},
	"pivot": {"x":0.5,"y":0.5}
},
{
	"filename": "shoe_6.png",
	"frame": {"x":1150,"y":1138,"w":101,"h":77},
	"rotated": false,
	"trimmed": false,
	"spriteSourceSize": {"x":0,"y":0,"w":101,"h":77},
	"sourceSize": {"w":101,"h":77},
	"pivot": {"x":0.5,"y":0.5}
}],
"meta": {
	"app": "http://www.codeandweb.com/texturepacker",
	"version": "1.0",
	"image": "state_dress_3.png",
	"format": "RGBA8888",
	"size": {"w":1929,"h":1333},
	"scale": "1",
	"smartupdate": "$TexturePacker:SmartUpdate:398ec214dbd0a5c7d9e0874b1f5f550f:9340ac4fece5b6956eff5061eca07b03:81b425fa12ba9dadca24fc32f839f626$"
}
}
